{"version":1,"resource":"vscode-remote://wsl%2Bubuntu/home/alejo/volumenCono.c","entries":[{"id":"KXO1.c","timestamp":1675136892673},{"id":"s8k2.c","timestamp":1675136972546},{"id":"XG3g.c","timestamp":1675136994039},{"id":"GEMg.c","timestamp":1675137436636},{"id":"PbG8.c","timestamp":1675139127100},{"id":"E9YI.c","timestamp":1675139214890},{"id":"DOc4.c","timestamp":1675139300640},{"id":"PuPq.c","timestamp":1675139332810},{"id":"pOFj.c","timestamp":1675139694070},{"id":"pI2u.c","timestamp":1675139879300},{"id":"kxV5.c","timestamp":1675140141790},{"id":"VDNE.c","timestamp":1675275479006},{"id":"WHns.c","timestamp":1675276167386},{"id":"IRPG.c","timestamp":1675276600886},{"id":"iSXM.c","timestamp":1675277412806},{"id":"WRRk.c","timestamp":1675575982424},{"id":"g0zp.c","timestamp":1675576089284},{"id":"5Mei.c","timestamp":1675599066504},{"id":"HeYA.c","timestamp":1675599598214},{"id":"yr03.c","timestamp":1675599897004}]}